{
  "current":1,
  "total":2,
  "pageNum": 1,
  "pageSize": 5,
  "data": {
    "list": [
      {
        "id": 1,
        "title": "一月"
      },
      {
        "id": 2,
        "title": "二月"
      },
      {
        "id": 3,
        "title": "三月"
      },
      {
        "id": 4,
        "title": "四月"
      },
      {
        "id": 5,
        "title": "五月"
      },
      {
        "id": 6,
        "title": "六月"
      },
      {
        "id": 7,
        "title": "七月"
      },
      {
        "id": 8,
        "title": "八月"
      },
      {
        "id": 9,
        "title": "九月"
      },
      {
        "id": 10,
        "title": "十月"
      },
      {
        "id": 11,
        "title": "十一月"
      },
      {
        "id": 12,
        "title": "十二月"
      }
    ]
  }
}
